{
  "action": {
    "description": "Authored by Senators Pol, Yoder, Hunley",
    "occurred_at": "2026-02-17",
    "jurisdiction_id": "~{\"classification\": \"upper\"}",
    "session_id": "2026",
    "entity_type": "bill",
    "classifications": [],
    "related_entities": [],
    "sources": [
      {
        "url": "https://iga.in.gov/legislative/2026/resolutions/senate/simple/50",
        "note": ""
      },
      {
        "url": "https://api.iga.in.gov/2026/bills/sr0050",
        "note": "API details"
      }
    ]
  },
  "bill_id": "SR 50"
}