{
  "action": {
    "description": "First reading: referred to Committee on Ways and Means",
    "occurred_at": "2026-01-05",
    "jurisdiction_id": "~{\"classification\": \"lower\"}",
    "session_id": "2026",
    "entity_type": "bill",
    "classifications": [
      "reading-1",
      "referral-committee"
    ],
    "related_entities": [
      {
        "name": "Ways and Means",
        "entity_type": "organization",
        "organization_id": null
      }
    ],
    "sources": [
      {
        "url": "https://iga.in.gov/legislative/2026/bills/house/1177",
        "note": ""
      },
      {
        "url": "https://api.iga.in.gov/2026/bills/hb1177",
        "note": "API details"
      }
    ]
  },
  "bill_id": "HB 1177"
}