{
  "action": {
    "description": "Senator Tomes added as cosponsor",
    "occurred_at": "2026-02-12",
    "jurisdiction_id": "~{\"classification\": \"upper\"}",
    "session_id": "2026",
    "entity_type": "bill",
    "classifications": [],
    "related_entities": [],
    "sources": [
      {
        "url": "https://iga.in.gov/legislative/2026/bills/house/1116",
        "note": ""
      },
      {
        "url": "https://api.iga.in.gov/2026/bills/hb1116",
        "note": "API details"
      }
    ]
  },
  "bill_id": "HB 1116"
}