{
  "legislative_session": "2026",
  "identifier": "HB 1213",
  "title": "Elimination of sales tax on household utility use.",
  "from_organization": "~{\"classification\": \"lower\"}",
  "classification": [
    "bill"
  ],
  "subject": [
    "TAXES; Sales and Use Taxes",
    "UTILITIES; Electric",
    "UTILITIES; Gas",
    "UTILITIES; Water"
  ],
  "abstracts": [
    {
      "note": "Digest",
      "abstract": "Provides that a power subsidiary or a person engaged as a public utility is not a retail merchant making a retail transaction when the subsidiary or person furnishes or sells electrical energy, natural or artificial gas, water, steam, or steam heating service to a person for domestic consumption."
    }
  ],
  "other_titles": [],
  "other_identifiers": [
    {
      "identifier": "ocd-bill-in-2026-hb1213"
    }
  ],
  "actions": [
    {
      "description": "First reading: referred to Committee on Ways and Means",
      "date": "2026-01-05",
      "organization_id": "~{\"classification\": \"lower\"}",
      "classification": [
        "reading-1",
        "referral-committee"
      ],
      "related_entities": [
        {
          "name": "Ways and Means",
          "entity_type": "organization",
          "organization_id": null
        }
      ],
      "_processing": {
        "log_file_created": "2026-07-14T13:57:15Z"
      }
    },
    {
      "description": "Authored by Representative Moed",
      "date": "2026-01-05",
      "organization_id": "~{\"classification\": \"lower\"}",
      "classification": [],
      "related_entities": [],
      "_processing": {
        "log_file_created": "2026-07-14T13:57:15Z"
      }
    }
  ],
  "sponsorships": [
    {
      "name": "Justin Moed",
      "classification": "author",
      "entity_type": "person",
      "primary": true,
      "person_id": "~{\"name\": \"Justin Moed\"}",
      "organization_id": null
    }
  ],
  "related_bills": [],
  "versions": [
    {
      "note": "Introduced House Bill (H)",
      "links": [
        {
          "url": "https://iga.in.gov/pdf-documents/124/2026/house/bills/HB1213/HB1213.01.INTR.pdf",
          "media_type": "application/pdf"
        }
      ],
      "date": "",
      "classification": ""
    }
  ],
  "documents": [
    {
      "note": "Fiscal Note: HB1213.01.INTR.FN001",
      "links": [
        {
          "url": "https://api.iga.in.gov/2026/fiscal-notes/HB1213.01.INTR/HB1213.01.INTR.FN001?format=pdf",
          "media_type": "application/pdf"
        }
      ],
      "date": "",
      "classification": ""
    }
  ],
  "citations": [],
  "sources": [
    {
      "url": "https://iga.in.gov/legislative/2026/bills/house/1213",
      "note": ""
    },
    {
      "url": "https://api.iga.in.gov/2026/bills/hb1213",
      "note": "API details"
    }
  ],
  "extras": {},
  "jurisdiction": {
    "id": "ocd-jurisdiction/country:us/state:in/government",
    "name": "Indiana",
    "classification": "state",
    "division_id": "ocd-division/country:us/state:in"
  },
  "_processing": {
    "logs_latest_update": "2026-07-14T13:57:15Z",
    "text_extraction_latest_update": "2026-07-14T21:50:25.874786Z"
  }
}